fast_bert/__init__.py
fast_bert/bert_layers.py
fast_bert/data.py
fast_bert/data_abs.py
fast_bert/data_cls.py
fast_bert/data_lm.py
fast_bert/data_ner.py
fast_bert/data_qa.py
fast_bert/learner_abs.py
fast_bert/learner_cls copy.py
fast_bert/learner_cls.py
fast_bert/learner_cls_old.py
fast_bert/learner_lm.py
fast_bert/learner_ner.py
fast_bert/learner_qa.py
fast_bert/learner_util.py
fast_bert/metrics.py
fast_bert/modeling.py
fast_bert/onnx_helper.py
fast_bert/optimization.py
fast_bert/prediction.py
fast_bert/prediction_ner.py
fast_bert/utils_squad_evaluate.py
fast_bert/summarisation/__init__.py
fast_bert/summarisation/configuration_bertabs.py
fast_bert/summarisation/modeling_bertabs.py
fast_bert/utils/__init__.py
fast_bert/utils/spellcheck.py
fast_bert-2.0.26.dist-info/LICENSE
fast_bert-2.0.26.dist-info/METADATA
fast_bert-2.0.26.dist-info/WHEEL
fast_bert-2.0.26.dist-info/top_level.txt
fast_bert-2.0.26.dist-info/RECORD
