Metadata-Version: 2.1
Name: fast_bert
Version: 2.0.26
Summary: AI Library using BERT
Home-page: https://github.com/kaushaltrivedi/fast-bert
Author: Kaushal Trivedi
Author-email: kaushaltrivedi@me.com
License: Apache2
Keywords: BERT NLP deep learning google
Classifier: Intended Audience :: Science/Research
Classifier: License :: OSI Approved :: Apache Software License
Classifier: Programming Language :: Python :: 3
Classifier: Topic :: Scientific/Engineering :: Artificial Intelligence
License-File: LICENSE
Requires-Dist: matplotlib
Requires-Dist: pytorch-lamb
Requires-Dist: tensorboardX
Requires-Dist: fastprogress
Requires-Dist: scikit-learn
Requires-Dist: seqeval
Requires-Dist: transformers (==4.22.*)
Requires-Dist: pandas
Requires-Dist: python-box
Requires-Dist: more-itertools
Requires-Dist: onnx
Requires-Dist: onnxruntime
Requires-Dist: onnxruntime-tools
